LICENSE.txt
MANIFEST.in
README.rst
requirements.txt
setup.py
fctdl/__init__.py
fctdl/__main__.py
fctdl/cli.py
fctdl/config.py
fctdl/factorio.py
fctdl.egg-info/PKG-INFO
fctdl.egg-info/SOURCES.txt
fctdl.egg-info/dependency_links.txt
fctdl.egg-info/entry_points.txt
fctdl.egg-info/requires.txt
fctdl.egg-info/top_level.txt