Metadata-Version: 1.0
Name: fctdl
Version: 0.1.1
Summary: Download factorio alpha from your command line
Home-page: https://github.com/afriemann/fctdl
Author: Aljosha Friemann
Author-email: aljosha.friemann@gmail.com
License: UNKNOWN
Keywords: factorio,cli,games,utility
Platform: linux
